botrun_gemini.py
botrun_gemini-4.6.264.dist-info/METADATA
botrun_gemini-4.6.264.dist-info/WHEEL
botrun_gemini-4.6.264.dist-info/entry_points.txt
botrun_gemini-4.6.264.dist-info/RECORD
