Metadata-Version: 2.3
Name: botrun_gemini
Version: 4.6.264
Requires-Dist: google-cloud-aiplatform
Requires-Dist: google-generativeai
Requires-Dist: python-dotenv
